{
	"metadata" : { "model" : "Breiman_CART", "version" : "2024-W13", "signature" : "ff4_il8"},
	"options" : { "ccp_alpha" : 0.000000, "criterion" : "", "max_depth" : 6, "max_features" : null, "max_leaf_nodes" : 32, "min_impurity_decrease" : 0.000000, "min_samples_leaf" : 1, "min_samples_split" : 2, "min_weight_fraction_leaf" : 0.000000, "random_state" : 1789, "splitter" : "best" },
	"dataset" : { "dataset_rows" : 512, "dataset_features" : 30 },
	"classes" : [ 0, 1 ],
	"tree" : {
	"features" : 30,
	"outputs" : 2,
	"max_depth" : 5,
	"node_count" : 33,
	"nodes" : {
		"node_00" : {"left" : 1, "right" : 2, "feature" : 22, "threshold" : 105.949997, "impurity" : 0.474335, "n_samples" : 512, "w_samples" : 512.000000, "value" : [0.386719, 0.613281]},
		"node_01" : {"left" : 11, "right" : 12, "feature" : 27, "threshold" : 0.158900, "impurity" : 0.099723, "n_samples" : 304, "w_samples" : 304.000000, "value" : [0.052632, 0.947368]},
		"node_02" : {"left" : 3, "right" : 4, "feature" : 7, "threshold" : 0.048865, "impurity" : 0.218750, "n_samples" : 208, "w_samples" : 208.000000, "value" : [0.875000, 0.125000]},
		"node_03" : {"left" : 5, "right" : 6, "feature" : 21, "threshold" : 29.130001, "impurity" : 0.480000, "n_samples" : 30, "w_samples" : 30.000000, "value" : [0.400000, 0.600000]},
		"node_04" : {"left" : 15, "right" : 16, "feature" : 21, "threshold" : 20.645000, "impurity" : 0.085848, "n_samples" : 178, "w_samples" : 178.000000, "value" : [0.955056, 0.044944]},
		"node_05" : {"left" : 7, "right" : 8, "feature" : 28, "threshold" : 0.314200, "impurity" : 0.255000, "n_samples" : 20, "w_samples" : 20.000000, "value" : [0.150000, 0.850000]},
		"node_06" : {"left" : 9, "right" : 10, "feature" : 16, "threshold" : 0.029795, "impurity" : 0.180000, "n_samples" : 10, "w_samples" : 10.000000, "value" : [0.900000, 0.100000]},
		"node_07" : {"left" : null, "right" : null, "feature" : null, "threshold" : null, "impurity" : 0.000000, "n_samples" : 17, "w_samples" : 17.000000, "value" : [0.000000, 1.000000]},
		"node_08" : {"left" : null, "right" : null, "feature" : null, "threshold" : null, "impurity" : 0.000000, "n_samples" : 3, "w_samples" : 3.000000, "value" : [1.000000, 0.000000]},
		"node_09" : {"left" : null, "right" : null, "feature" : null, "threshold" : null, "impurity" : 0.000000, "n_samples" : 9, "w_samples" : 9.000000, "value" : [1.000000, 0.000000]},
		"node_10" : {"left" : null, "right" : null, "feature" : null, "threshold" : null, "impurity" : 0.000000, "n_samples" : 1, "w_samples" : 1.000000, "value" : [0.000000, 1.000000]},
		"node_11" : {"left" : 21, "right" : 22, "feature" : 10, "threshold" : 1.047550, "impurity" : 0.046640, "n_samples" : 293, "w_samples" : 293.000000, "value" : [0.023891, 0.976109]},
		"node_12" : {"left" : 13, "right" : 14, "feature" : 21, "threshold" : 23.470001, "impurity" : 0.297521, "n_samples" : 11, "w_samples" : 11.000000, "value" : [0.818182, 0.181818]},
		"node_13" : {"left" : null, "right" : null, "feature" : null, "threshold" : null, "impurity" : 0.000000, "n_samples" : 2, "w_samples" : 2.000000, "value" : [0.000000, 1.000000]},
		"node_14" : {"left" : null, "right" : null, "feature" : null, "threshold" : null, "impurity" : 0.000000, "n_samples" : 9, "w_samples" : 9.000000, "value" : [1.000000, 0.000000]},
		"node_15" : {"left" : 17, "right" : 18, "feature" : 22, "threshold" : 119.650002, "impurity" : 0.497778, "n_samples" : 15, "w_samples" : 15.000000, "value" : [0.533333, 0.466667]},
		"node_16" : {"left" : 19, "right" : 20, "feature" : 19, "threshold" : 0.012910, "impurity" : 0.012195, "n_samples" : 163, "w_samples" : 163.000000, "value" : [0.993865, 0.006135]},
		"node_17" : {"left" : null, "right" : null, "feature" : null, "threshold" : null, "impurity" : 0.000000, "n_samples" : 7, "w_samples" : 7.000000, "value" : [0.000000, 1.000000]},
		"node_18" : {"left" : null, "right" : null, "feature" : null, "threshold" : null, "impurity" : 0.000000, "n_samples" : 8, "w_samples" : 8.000000, "value" : [1.000000, 0.000000]},
		"node_19" : {"left" : null, "right" : null, "feature" : null, "threshold" : null, "impurity" : 0.000000, "n_samples" : 162, "w_samples" : 162.000000, "value" : [1.000000, 0.000000]},
		"node_20" : {"left" : null, "right" : null, "feature" : null, "threshold" : null, "impurity" : 0.000000, "n_samples" : 1, "w_samples" : 1.000000, "value" : [0.000000, 1.000000]},
		"node_21" : {"left" : 23, "right" : 24, "feature" : 24, "threshold" : 0.178250, "impurity" : 0.040251, "n_samples" : 292, "w_samples" : 292.000000, "value" : [0.020548, 0.979452]},
		"node_22" : {"left" : null, "right" : null, "feature" : null, "threshold" : null, "impurity" : 0.000000, "n_samples" : 1, "w_samples" : 1.000000, "value" : [1.000000, 0.000000]},
		"node_23" : {"left" : 27, "right" : 28, "feature" : 21, "threshold" : 30.145000, "impurity" : 0.027392, "n_samples" : 288, "w_samples" : 288.000000, "value" : [0.013889, 0.986111]},
		"node_24" : {"left" : 25, "right" : 26, "feature" : 23, "threshold" : 421.049988, "impurity" : 0.500000, "n_samples" : 4, "w_samples" : 4.000000, "value" : [0.500000, 0.500000]},
		"node_25" : {"left" : null, "right" : null, "feature" : null, "threshold" : null, "impurity" : 0.000000, "n_samples" : 2, "w_samples" : 2.000000, "value" : [0.000000, 1.000000]},
		"node_26" : {"left" : null, "right" : null, "feature" : null, "threshold" : null, "impurity" : 0.000000, "n_samples" : 2, "w_samples" : 2.000000, "value" : [1.000000, 0.000000]},
		"node_27" : {"left" : 31, "right" : 32, "feature" : 13, "threshold" : 48.974998, "impurity" : 0.007722, "n_samples" : 258, "w_samples" : 258.000000, "value" : [0.003876, 0.996124]},
		"node_28" : {"left" : 29, "right" : 30, "feature" : 20, "threshold" : 15.770000, "impurity" : 0.180000, "n_samples" : 30, "w_samples" : 30.000000, "value" : [0.100000, 0.900000]},
		"node_29" : {"left" : null, "right" : null, "feature" : null, "threshold" : null, "impurity" : 0.068878, "n_samples" : 28, "w_samples" : 28.000000, "value" : [0.035714, 0.964286]},
		"node_30" : {"left" : null, "right" : null, "feature" : null, "threshold" : null, "impurity" : 0.000000, "n_samples" : 2, "w_samples" : 2.000000, "value" : [1.000000, 0.000000]},
		"node_31" : {"left" : null, "right" : null, "feature" : null, "threshold" : null, "impurity" : 0.000000, "n_samples" : 254, "w_samples" : 254.000000, "value" : [0.000000, 1.000000]},
		"node_32" : {"left" : null, "right" : null, "feature" : null, "threshold" : null, "impurity" : 0.375000, "n_samples" : 4, "w_samples" : 4.000000, "value" : [0.250000, 0.750000]}
		}
	}
}