{
   "Contributions" : {
      "X_0" : [ -0.012207, 0.012207 ],
      "X_1" : [ 0.026367, -0.026367 ],
      "X_2" : [ -0.001465, 0.001465 ],
      "X_3" : [ -0.043457, 0.043457 ],
      "X_4" : [ 0.000000, 0.000000 ],
      "X_5" : [ -0.032227, 0.032227 ],
      "X_6" : [ 0.000000, 0.000000 ],
      "X_7" : [ 0.000000, 0.000000 ],
      "X_8" : [ 0.004395, -0.004395 ],
      "X_9" : [ -0.013672, 0.013672 ]   
   },
   "Most_Contributive_Features_By_Class" : {
      "class_0" : [ 3, 5, 1, 9, 0, 8, 2 ],
      "class_1" : [ 3, 5, 1, 9, 0, 8, 2 ]
   }
}